{"errors":[],"warnings":[],"namedChunkGroups":{"app":{"chunks":[5,0,2],"assets":["webpack-runtime-8b6668d23fbf0e0cabe0.js","webpack-runtime-8b6668d23fbf0e0cabe0.js.map","commons-c0e2a9dc71d2639cb193.js","commons-c0e2a9dc71d2639cb193.js.map","app-46ddbb1cba48c46df357.js","app-46ddbb1cba48c46df357.js.map"],"children":{},"childAssets":{}},"component---src-pages-404-jsx":{"chunks":[1,0,3],"assets":["styles.d575d2589fae6b34368b.css","styles-4b49d8bfdd28576a4215.js","styles-4b49d8bfdd28576a4215.js.map","commons-c0e2a9dc71d2639cb193.js","commons-c0e2a9dc71d2639cb193.js.map","component---src-pages-404-jsx-e5b9e6117f6cab18920e.js","component---src-pages-404-jsx-e5b9e6117f6cab18920e.js.map"],"children":{},"childAssets":{}},"component---src-pages-index-jsx":{"chunks":[1,0,4],"assets":["styles.d575d2589fae6b34368b.css","styles-4b49d8bfdd28576a4215.js","styles-4b49d8bfdd28576a4215.js.map","commons-c0e2a9dc71d2639cb193.js","commons-c0e2a9dc71d2639cb193.js.map","component---src-pages-index-jsx-f275bb36eae8b4104620.js","component---src-pages-index-jsx-f275bb36eae8b4104620.js.map"],"children":{},"childAssets":{}}},"assetsByChunkName":{"app":["webpack-runtime-8b6668d23fbf0e0cabe0.js","commons-c0e2a9dc71d2639cb193.js","app-46ddbb1cba48c46df357.js"],"component---src-pages-404-jsx":["styles.d575d2589fae6b34368b.css","styles-4b49d8bfdd28576a4215.js","commons-c0e2a9dc71d2639cb193.js","component---src-pages-404-jsx-e5b9e6117f6cab18920e.js"],"component---src-pages-index-jsx":["styles.d575d2589fae6b34368b.css","styles-4b49d8bfdd28576a4215.js","commons-c0e2a9dc71d2639cb193.js","component---src-pages-index-jsx-f275bb36eae8b4104620.js"]}}